odoo/addons/fieldservice_sale_agreement/README.rst
odoo/addons/fieldservice_sale_agreement/__init__.py
odoo/addons/fieldservice_sale_agreement/__manifest__.py
odoo/addons/fieldservice_sale_agreement/i18n/fieldservice_sale_agreement.pot
odoo/addons/fieldservice_sale_agreement/i18n/it.po
odoo/addons/fieldservice_sale_agreement/models/__init__.py
odoo/addons/fieldservice_sale_agreement/models/sale_order.py
odoo/addons/fieldservice_sale_agreement/readme/CONTRIBUTORS.md
odoo/addons/fieldservice_sale_agreement/readme/DESCRIPTION.md
odoo/addons/fieldservice_sale_agreement/static/description/icon.png
odoo/addons/fieldservice_sale_agreement/static/description/index.html
odoo/addons/fieldservice_sale_agreement/tests/__init__.py
odoo/addons/fieldservice_sale_agreement/tests/test_fsm_sale_agreement.py
odoo_addon_fieldservice_sale_agreement-18.0.1.0.0.2.dist-info/METADATA
odoo_addon_fieldservice_sale_agreement-18.0.1.0.0.2.dist-info/WHEEL
odoo_addon_fieldservice_sale_agreement-18.0.1.0.0.2.dist-info/top_level.txt
odoo_addon_fieldservice_sale_agreement-18.0.1.0.0.2.dist-info/RECORD
